mystai/__init__.py
myst_ai-0.0.1.dist-info/LICENSE
myst_ai-0.0.1.dist-info/METADATA
myst_ai-0.0.1.dist-info/WHEEL
myst_ai-0.0.1.dist-info/top_level.txt
myst_ai-0.0.1.dist-info/RECORD
